scripts/__init__.py
scripts/djsearch.py
dj_image_search-0.1.1.dist-info/METADATA
dj_image_search-0.1.1.dist-info/WHEEL
dj_image_search-0.1.1.dist-info/entry_points.txt
dj_image_search-0.1.1.dist-info/top_level.txt
dj_image_search-0.1.1.dist-info/RECORD
