Metadata-Version: 2.1
Name: dj-image-search
Version: 0.1.1
Requires-Dist: click
Requires-Dist: keyboard
Requires-Dist: climage
Requires-Dist: urllib3
Requires-Dist: google-search-results
